sb_arch_opt/__init__.py
sb_arch_opt/correction.py
sb_arch_opt/design_space.py
sb_arch_opt/design_space_explicit.py
sb_arch_opt/pareto_front.py
sb_arch_opt/problem.py
sb_arch_opt/sampling.py
sb_arch_opt/util.py
sb_arch_opt/algo/__init__.py
sb_arch_opt/algo/arch_sbo/__init__.py
sb_arch_opt/algo/arch_sbo/algo.py
sb_arch_opt/algo/arch_sbo/api.py
sb_arch_opt/algo/arch_sbo/hc_strategy.py
sb_arch_opt/algo/arch_sbo/infill.py
sb_arch_opt/algo/arch_sbo/metrics.py
sb_arch_opt/algo/arch_sbo/models.py
sb_arch_opt/algo/botorch_interface/__init__.py
sb_arch_opt/algo/botorch_interface/algo.py
sb_arch_opt/algo/botorch_interface/api.py
sb_arch_opt/algo/egor_interface/__init__.py
sb_arch_opt/algo/egor_interface/algo.py
sb_arch_opt/algo/egor_interface/api.py
sb_arch_opt/algo/hebo_interface/__init__.py
sb_arch_opt/algo/hebo_interface/algo.py
sb_arch_opt/algo/hebo_interface/api.py
sb_arch_opt/algo/pymoo_interface/__init__.py
sb_arch_opt/algo/pymoo_interface/api.py
sb_arch_opt/algo/pymoo_interface/md_mating.py
sb_arch_opt/algo/pymoo_interface/metrics.py
sb_arch_opt/algo/pymoo_interface/random_search.py
sb_arch_opt/algo/pymoo_interface/storage_restart.py
sb_arch_opt/algo/segomoe_interface/__init__.py
sb_arch_opt/algo/segomoe_interface/algo.py
sb_arch_opt/algo/segomoe_interface/api.py
sb_arch_opt/algo/segomoe_interface/pymoo_algo.py
sb_arch_opt/algo/smarty_interface/__init__.py
sb_arch_opt/algo/smarty_interface/algo.py
sb_arch_opt/algo/smarty_interface/api.py
sb_arch_opt/algo/tpe_interface/__init__.py
sb_arch_opt/algo/tpe_interface/api.py
sb_arch_opt/algo/trieste_interface/__init__.py
sb_arch_opt/algo/trieste_interface/algo.py
sb_arch_opt/algo/trieste_interface/api.py
sb_arch_opt/problems/__init__.py
sb_arch_opt/problems/assignment.py
sb_arch_opt/problems/constrained.py
sb_arch_opt/problems/continuous.py
sb_arch_opt/problems/discrete.py
sb_arch_opt/problems/gnc.py
sb_arch_opt/problems/hidden_constraints.py
sb_arch_opt/problems/hierarchical.py
sb_arch_opt/problems/md_mo.py
sb_arch_opt-1.5.7.dist-info/licenses/LICENSE
sb_arch_opt-1.5.7.dist-info/METADATA
sb_arch_opt-1.5.7.dist-info/WHEEL
sb_arch_opt-1.5.7.dist-info/top_level.txt
sb_arch_opt-1.5.7.dist-info/RECORD
