Metadata-Version: 2.4
Name: sb-arch-opt
Version: 1.5.7
Summary: SBArchOpt: Surrogate-Based Architecture Optimization
Author: Jasper Bussemaker
Author-email: jasper.bussemaker@dlr.de
License: MIT
Classifier: Intended Audience :: Science/Research
Classifier: Topic :: Scientific/Engineering
Classifier: Programming Language :: Python :: 3
Classifier: License :: OSI Approved :: MIT License
Requires-Python: >=3.7
License-File: LICENSE
Requires-Dist: numpy<2.0
Requires-Dist: pymoo~=0.6.1
Requires-Dist: scipy
Requires-Dist: deprecated
Requires-Dist: pandas
Requires-Dist: cached-property~=1.5
Requires-Dist: ConfigSpace~=1.2.1
Requires-Dist: more-itertools~=9.1
Requires-Dist: appdirs
Provides-Extra: arch-sbo
Requires-Dist: smt!=2.10.0,!=2.4,~=2.2; extra == "arch-sbo"
Requires-Dist: jenn~=1.0; extra == "arch-sbo"
Requires-Dist: numba; extra == "arch-sbo"
Requires-Dist: scikit-learn; extra == "arch-sbo"
Provides-Extra: botorch
Requires-Dist: ax-platform~=0.3.0; extra == "botorch"
Requires-Dist: botorch~=0.8.2; extra == "botorch"
Provides-Extra: trieste
Requires-Dist: trieste~=4.5; extra == "trieste"
Provides-Extra: hebo
Requires-Dist: HEBO; extra == "hebo"
Provides-Extra: rocket
Requires-Dist: ambiance; extra == "rocket"
Provides-Extra: egor
Requires-Dist: egobox~=0.14.0; extra == "egor"
Dynamic: author
Dynamic: author-email
Dynamic: classifier
Dynamic: description
Dynamic: description-content-type
Dynamic: license
Dynamic: license-file
Dynamic: provides-extra
Dynamic: requires-dist
Dynamic: requires-python
Dynamic: summary
